napari_labels_overlap/__init__.py
napari_labels_overlap/_dock_widget.py
napari_labels_overlap/napari.yaml
napari_labels_overlap/_tests/__init__.py
napari_labels_overlap/_tests/test_dock_widget.py
napari_labels_overlap-0.0.3.dist-info/LICENSE
napari_labels_overlap-0.0.3.dist-info/METADATA
napari_labels_overlap-0.0.3.dist-info/WHEEL
napari_labels_overlap-0.0.3.dist-info/entry_points.txt
napari_labels_overlap-0.0.3.dist-info/top_level.txt
napari_labels_overlap-0.0.3.dist-info/RECORD
