Metadata-Version: 2.1
Name: napari-labels-overlap
Version: 0.0.3
Summary: create an overlap labels layer from two labels layers
Home-page: https://github.com/chili-chiu/napari-labels-overlap
Author: Chi-Li Chiu
Author-email: cchiu@chanzuckerberg.com
License: BSD-3-Clause
Project-URL: Bug Tracker, https://github.com/chili-chiu/napari-labels-overlap/issues
Project-URL: Documentation, https://github.com/chili-chiu/napari-labels-overlap#README.md
Project-URL: Source Code, https://github.com/chili-chiu/napari-labels-overlap
Project-URL: User Support, https://github.com/chili-chiu/napari-labels-overlap/issues
Classifier: Development Status :: 2 - Pre-Alpha
Classifier: Intended Audience :: Developers
Classifier: Framework :: napari
Classifier: Topic :: Software Development :: Testing
Classifier: Programming Language :: Python
Classifier: Programming Language :: Python :: 3
Classifier: Programming Language :: Python :: 3.7
Classifier: Programming Language :: Python :: 3.8
Classifier: Programming Language :: Python :: 3.9
Classifier: Operating System :: OS Independent
Classifier: License :: OSI Approved :: BSD License
Requires-Python: >=3.7
License-File: LICENSE
Requires-Dist: scikit-image
